util/adder_testsuites/tb_master.v
// TB master: generate inputs for test bench


// Xilinx requires timescale in all source files
`timescale 1ps/1ps

module tb_master 
	# ( parameter
		data_width = 8
	)
	(
	input wire clk,
	input wire rst,

	// outputs: generated inputs for DUT
	output reg [data_width - 1 : 0] reg_a,
	output reg [data_width - 1 : 0] reg_b,

	// input: outputs of DUT
	input wire [data_width : 0] inp
	);

	

	// file handles
	integer infile, outfile;
	// status of file input
	integer statusI;

	integer in_a, in_b;
	integer count = 0;

	// open and check files
	initial begin
		infile = $fopen("input.txt", "r");
		outfile = $fopen("output.txt", "w");
		if (0 == infile) begin
			$display("ERROR: could not read input.txt");
			$finish();
		end
		if (0 == outfile) begin
			$display("ERROR: could not open output.txt");
			$finish();
		end
	end


	// write outputs to file, then read inputs from file
	always @ (posedge clk) begin
		if (rst) begin
			reg_a <= 0;
			reg_b <= 0;
		end
		if (~rst) begin
			count <= count + 1;
			if (count > 0) begin
				$fwrite(outfile, "%d %d -> %d\n", reg_a, reg_b, inp);
			end
			// print inputs and outputs on each cycle
			$display($time, ": a=%d, b=%d => =%d", reg_a, reg_b, inp);
			// read inputs from file
			statusI = $fscanf(infile, "%d %d\n", reg_a, reg_b);
			//statusI = $fscanf(infile, "%d %d\n", in_a, in_b);
			//reg_a <= in_a;
			//reg_b <= in_b;
		end
	end


endmodule

util/pipelined_adder.v
// take 2 inputs of width INP_DW, gives 1 output of width INP_DW+1

module pipelined_adder
    #(parameter
        INP_DW = 8,
        NUM_REG = 4
    )
    (
        input wire clk,
        input wire [INP_DW-1:0] inp1,
        input wire [INP_DW-1:0] inp2,
        output wire [INP_DW:0] outp
    );

    reg[INP_DW:0] regs [1:NUM_REG];
    reg [NUM_REG-1:0] i;   //ideally, width should be number of bits required to contain (NUM_REG-1); 
                           //ie $bits(NUM_REG-1) but $bits doesn't do what we thought it does.
    
    always@(posedge clk) begin
        regs[1] <= inp1 + inp2; 
        for(i = 2; i <= NUM_REG; i = i+1) begin 
            regs[i] <= regs[i-1];
        end
    end

    assign outp = regs[NUM_REG];

endmodule

util/adder_testsuites/tb.v
// TB: test bench

`timescale 1ps/1ps

// set global data bitwidth
`define DATA_WIDTH    3

// test bench
module tb ();

	localparam TB_TIMEOUT =  100_000;  // timeout 100ns
	localparam TB_CLK_PERIOD = 2_000;  // clock period 2ns
	localparam TB_RST_PERIOD = 4_000;  // reset period 4ns


	// clock
	reg tb_clk = 1'b0;
	always #(TB_CLK_PERIOD / 2) tb_clk = ~tb_clk;
	//reset
	reg tb_rst = 1'b1;
	initial begin
		#(TB_RST_PERIOD) tb_rst = 1'b0;
	end

	// dump
	initial begin
		$dumpvars;
	end
	
	// timeout
	initial #(TB_TIMEOUT) begin
		//$display("close files...");
		//$fclose(infile);
		//$fclose(outfile);
		//$display("...done");
		$finish();
		//$display("after finish");
	end

	localparam data_width = `DATA_WIDTH;

	// DUT
	wire [data_width - 1 : 0] dut_inp_a;
	wire [data_width - 1 : 0] dut_inp_b;
	wire [data_width : 0] dut_outp;

        pipelined_adder	 
		# (
			.INP_DW(data_width)
		)
		DUT 
		(
                .clk(tb_clk),
		.inp1(dut_inp_a),
		.inp2(dut_inp_b),
		.outp(dut_outp)
		);

	// tb_master to drive DUT and receive its output
	tb_master
		# (
			.data_width(data_width)
		)
		tb_master
		(
			.clk(tb_clk),
			.rst(tb_rst),
			.reg_a(dut_inp_a),
			.reg_b(dut_inp_b),
			.inp(dut_outp)
		);


endmodule

util/adder_testsuites/dump.vcd
$date
	Mon Jul 25 21:01:27 2016
$end
$version
	Icarus Verilog
$end
$timescale
	1ps
$end
$scope module tb $end
$var wire 3 ! dut_inp_a [2:0] $end
$var wire 3 " dut_inp_b [2:0] $end
$var wire 4 # dut_outp [3:0] $end
$var reg 1 $ tb_clk $end
$var reg 1 % tb_rst $end
$scope module DUT $end
$var wire 1 & clk $end
$var wire 3 ' inp1 [2:0] $end
$var wire 3 ( inp2 [2:0] $end
$var wire 4 ) outp [3:0] $end
$var reg 4 * i [3:0] $end
$upscope $end
$scope module tb_master $end
$var wire 1 & clk $end
$var wire 4 + inp [3:0] $end
$var wire 1 , rst $end
$var integer 32 - count [31:0] $end
$var integer 32 . infile [31:0] $end
$var integer 32 / outfile [31:0] $end
$var reg 3 0 reg_a [2:0] $end
$var reg 3 1 reg_b [2:0] $end
$var integer 32 2 statusI [31:0] $end
$upscope $end
$upscope $end
$enddefinitions $end
#0
$dumpvars
bx 2
bx 1
bx 0
b10000000000000000000000000000100 /
b10000000000000000000000000000011 .
b0 -
1,
bz +
bx *
bz )
bx (
bx '
0&
1%
0$
bz #
bx "
bx !
$end
#1000
bx #
bx )
bx +
b0 1
b0 "
b0 (
b0 0
b0 !
b0 '
b101 *
1$
1&
#2000
0$
0&
#3000
b101 *
1$
1&
#4000
0$
0&
0%
0,
#5000
b1 -
b101 *
b10 2
1$
1&
#6000
0$
0&
#7000
b10 -
b1 1
b1 "
b1 (
b101 *
1$
1&
#8000
0$
0&
#9000
b0 #
b0 )
b0 +
b11 -
b101 *
b10 1
b10 "
b10 (
1$
1&
#10000
0$
0&
#11000
b100 -
b11 1
b11 "
b11 (
b101 *
1$
1&
#12000
0$
0&
#13000
b101 -
b101 *
b100 1
b100 "
b100 (
1$
1&
#14000
0$
0&
#15000
b110 -
b10 #
b10 )
b10 +
b101 1
b101 "
b101 (
b101 *
1$
1&
#16000
0$
0&
#17000
b111 -
b101 *
b110 1
b110 "
b110 (
1$
1&
#18000
0$
0&
#19000
b1000 -
b100 #
b100 )
b100 +
b111 1
b111 "
b111 (
b101 *
1$
1&
#20000
0$
0&
#21000
b1001 -
b101 *
b0 1
b0 "
b0 (
b1 0
b1 !
b1 '
1$
1&
#22000
0$
0&
#23000
b1010 -
b110 #
b110 )
b110 +
b1 1
b1 "
b1 (
b101 *
1$
1&
#24000
0$
0&
#25000
b1011 -
b101 *
b10 1
b10 "
b10 (
1$
1&
#26000
0$
0&
#27000
b1100 -
b1 #
b1 )
b1 +
b11 1
b11 "
b11 (
b101 *
1$
1&
#28000
0$
0&
#29000
b1101 -
b101 *
b100 1
b100 "
b100 (
1$
1&
#30000
0$
0&
#31000
b1110 -
b11 #
b11 )
b11 +
b101 1
b101 "
b101 (
b101 *
1$
1&
#32000
0$
0&
#33000
b1111 -
b101 *
b110 1
b110 "
b110 (
1$
1&
#34000
0$
0&
#35000
b10000 -
b101 #
b101 )
b101 +
b111 1
b111 "
b111 (
b101 *
1$
1&
#36000
0$
0&
#37000
b10001 -
b101 *
b0 1
b0 "
b0 (
b10 0
b10 !
b10 '
1$
1&
#38000
0$
0&
#39000
b10010 -
b111 #
b111 )
b111 +
b1 1
b1 "
b1 (
b101 *
1$
1&
#40000
0$
0&
#41000
b10011 -
b101 *
b10 1
b10 "
b10 (
1$
1&
#42000
0$
0&
#43000
b10100 -
b10 #
b10 )
b10 +
b11 1
b11 "
b11 (
b101 *
1$
1&
#44000
0$
0&
#45000
b10101 -
b101 *
b100 1
b100 "
b100 (
1$
1&
#46000
0$
0&
#47000
b10110 -
b100 #
b100 )
b100 +
b101 1
b101 "
b101 (
b101 *
1$
1&
#48000
0$
0&
#49000
b10111 -
b101 *
b110 1
b110 "
b110 (
1$
1&
#50000
0$
0&
#51000
b11000 -
b110 #
b110 )
b110 +
b111 1
b111 "
b111 (
b101 *
1$
1&
#52000
0$
0&
#53000
b11001 -
b101 *
b0 1
b0 "
b0 (
b11 0
b11 !
b11 '
1$
1&
#54000
0$
0&
#55000
b11010 -
b1000 #
b1000 )
b1000 +
b1 1
b1 "
b1 (
b101 *
1$
1&
#56000
0$
0&
#57000
b11011 -
b101 *
b10 1
b10 "
b10 (
1$
1&
#58000
0$
0&
#59000
b11100 -
b11 #
b11 )
b11 +
b11 1
b11 "
b11 (
b101 *
1$
1&
#60000
0$
0&
#61000
b11101 -
b101 *
b100 1
b100 "
b100 (
1$
1&
#62000
0$
0&
#63000
b11110 -
b101 #
b101 )
b101 +
b101 1
b101 "
b101 (
b101 *
1$
1&
#64000
0$
0&
#65000
b11111 -
b101 *
b110 1
b110 "
b110 (
1$
1&
#66000
0$
0&
#67000
b100000 -
b111 #
b111 )
b111 +
b111 1
b111 "
b111 (
b101 *
1$
1&
#68000
0$
0&
#69000
b100001 -
b101 *
b0 1
b0 "
b0 (
b100 0
b100 !
b100 '
1$
1&
#70000
0$
0&
#71000
b100010 -
b1001 #
b1001 )
b1001 +
b1 1
b1 "
b1 (
b101 *
1$
1&
#72000
0$
0&
#73000
b100011 -
b101 *
b10 1
b10 "
b10 (
1$
1&
#74000
0$
0&
#75000
b100100 -
b100 #
b100 )
b100 +
b11 1
b11 "
b11 (
b101 *
1$
1&
#76000
0$
0&
#77000
b100101 -
b101 *
b100 1
b100 "
b100 (
1$
1&
#78000
0$
0&
#79000
b100110 -
b110 #
b110 )
b110 +
b101 1
b101 "
b101 (
b101 *
1$
1&
#80000
0$
0&
#81000
b100111 -
b101 *
b110 1
b110 "
b110 (
1$
1&
#82000
0$
0&
#83000
b101000 -
b1000 #
b1000 )
b1000 +
b111 1
b111 "
b111 (
b101 *
1$
1&
#84000
0$
0&
#85000
b101001 -
b101 *
b0 1
b0 "
b0 (
b101 0
b101 !
b101 '
1$
1&
#86000
0$
0&
#87000
b101010 -
b1010 #
b1010 )
b1010 +
b1 1
b1 "
b1 (
b101 *
1$
1&
#88000
0$
0&
#89000
b101011 -
b101 *
b10 1
b10 "
b10 (
1$
1&
#90000
0$
0&
#91000
b101100 -
b101 #
b101 )
b101 +
b11 1
b11 "
b11 (
b101 *
1$
1&
#92000
0$
0&
#93000
b101101 -
b101 *
b100 1
b100 "
b100 (
1$
1&
#94000
0$
0&
#95000
b101110 -
b111 #
b111 )
b111 +
b101 1
b101 "
b101 (
b101 *
1$
1&
#96000
0$
0&
#97000
b101111 -
b101 *
b110 1
b110 "
b110 (
1$
1&
#98000
0$
0&
#99000
b110000 -
b1001 #
b1001 )
b1001 +
b111 1
b111 "
b111 (
b101 *
1$
1&
