util/adder_testsuites/tb_master.v
// TB master: generate inputs for test bench

module tb_master 
	# ( parameter
		data_width = 8
	)
	(
	input wire clk,
	input wire rst,

	// outputs: generated inputs for DUT
	output reg [data_width - 1 : 0] reg_a,
	output reg [data_width - 1 : 0] reg_b,

	// input: outputs of DUT
	input wire [data_width : 0] inp
	);

	

	// file handles
	integer infile, outfile;
	// status of file input
	integer statusI;

	integer in_a, in_b;
	integer count = 0;

	// open and check files
	initial begin
		infile = $fopen("input.txt", "r");
		outfile = $fopen("output.txt", "w");
		if (0 == infile) begin
			$display("ERROR: could not read input.txt");
			$finish();
		end
		if (0 == outfile) begin
			$display("ERROR: could not open output.txt");
			$finish();
		end
	end


	// write outputs to file, then read inputs from file
	always @ (posedge clk) begin
		if (rst) begin
			reg_a <= 0;
			reg_b <= 0;
		end
		if (~rst) begin
			count <= count + 1;
			if (count > 0) begin
				$fwrite(outfile, "%d %d -> %d\n", reg_a, reg_b, inp);
			end
			// print inputs and outputs on each cycle
			#(1_000)$display($time, ": a=%d, b=%d => =%d", reg_a, reg_b, inp);   //added delay to give time to DUT because DUT uses clk as well
			// read inputs from file
			statusI = $fscanf(infile, "%d %d\n", reg_a, reg_b);
			//statusI = $fscanf(infile, "%d %d\n", in_a, in_b);
			//reg_a <= in_a;
			//reg_b <= in_b;
		end
	end


endmodule

util/pipelined_adder.v
// take 2 inputs of width INP_DW, gives 1 output of width INP_DW+1

module pipelined_adder
    #(parameter
        INP_DW = 8,
        NUM_REG = 4
    )
    (
        input wire clk,
        input wire [INP_DW-1:0] inp1,
        input wire [INP_DW-1:0] inp2,
        output wire [INP_DW:0] outp
    );

    reg[INP_DW:0] regs [1:NUM_REG];
    reg [NUM_REG-1:0] i;   //ideally, width should be number of bits required to contain (NUM_REG-1); 
                           //ie $bits(NUM_REG-1) but $bits doesn't do what we thought it does.
    
    always@(posedge clk) begin
        regs[1] <= inp1 + inp2; 
        for(i = 2; i <= NUM_REG; i = i+1) begin 
            regs[i] <= regs[i-1];
        end
    end

    assign outp = regs[NUM_REG];

endmodule

util/adder_testsuites/tb.v
// TB: test bench

`timescale 1ps/1ps

// set global data bitwidth
`define DATA_WIDTH    3

// test bench
module tb ();

	localparam TB_TIMEOUT =  100_000;  // timeout 100ns
	localparam TB_CLK_PERIOD = 2_000;  // clock period 2ns
	localparam TB_RST_PERIOD = 4_000;  // reset period 4ns


	// clock
	reg tb_clk = 1'b0;
	always #(TB_CLK_PERIOD / 2) tb_clk = ~tb_clk;
        // clock
	reg tb_clk2 = 1'b0;
	always #(TB_CLK_PERIOD / 3) tb_clk2 = ~tb_clk2;
	//reset
	reg tb_rst = 1'b1;
	initial begin
		#(TB_RST_PERIOD) tb_rst = 1'b0;
	end

	// dump
	initial begin
		$dumpvars;
	end
	
	// timeout
	initial #(TB_TIMEOUT) begin
		//$display("close files...");
		//$fclose(infile);
		//$fclose(outfile);
		//$display("...done");
		$finish();
		//$display("after finish");
	end

	localparam data_width = `DATA_WIDTH;

	// DUT
	wire [data_width - 1 : 0] dut_inp_a;
	wire [data_width - 1 : 0] dut_inp_b;
	wire [data_width : 0] dut_outp;

        pipelined_adder	 
		# (
			.INP_DW(data_width),
                        .NUM_REG(2)
		)
		DUT 
		(
                .clk(tb_clk),
		.inp1(dut_inp_a),
		.inp2(dut_inp_b),
		.outp(dut_outp)
		);

	// tb_master to drive DUT and receive its output
	tb_master
		# (
			.data_width(data_width)
		)
		tb_master
		(
			.clk(tb_clk),
			.rst(tb_rst),
			.reg_a(dut_inp_a),
			.reg_b(dut_inp_b),
			.inp(dut_outp)
		);


endmodule

util/adder_testsuites/dump.vcd
$date
	Tue Jul 26 18:12:47 2016
$end
$version
	Icarus Verilog
$end
$timescale
	1ps
$end
$scope module tb $end
$var wire 3 ! dut_inp_a [2:0] $end
$var wire 3 " dut_inp_b [2:0] $end
$var wire 4 # dut_outp [3:0] $end
$var reg 1 $ tb_clk $end
$var reg 1 % tb_clk2 $end
$var reg 1 & tb_rst $end
$scope module DUT $end
$var wire 1 ' clk $end
$var wire 3 ( inp1 [2:0] $end
$var wire 3 ) inp2 [2:0] $end
$var wire 4 * outp [3:0] $end
$var reg 2 + i [1:0] $end
$upscope $end
$scope module tb_master $end
$var wire 1 ' clk $end
$var wire 4 , inp [3:0] $end
$var wire 1 - rst $end
$var integer 32 . count [31:0] $end
$var integer 32 / infile [31:0] $end
$var integer 32 0 outfile [31:0] $end
$var reg 3 1 reg_a [2:0] $end
$var reg 3 2 reg_b [2:0] $end
$var integer 32 3 statusI [31:0] $end
$upscope $end
$upscope $end
$enddefinitions $end
#0
$dumpvars
bx 3
bx 2
bx 1
b10000000000000000000000000000100 0
b10000000000000000000000000000011 /
b0 .
1-
bz ,
bx +
bz *
bx )
bx (
0'
1&
0%
0$
bz #
bx "
bx !
$end
#666
1%
#1000
bx #
bx *
bx ,
b0 2
b0 "
b0 )
b0 1
b0 !
b0 (
b11 +
1$
1'
#1332
0%
#1998
1%
#2000
0$
0'
#2664
0%
#3000
b11 +
1$
1'
#3330
1%
#3996
0%
#4000
0$
0'
0&
0-
#4662
1%
#5000
b0 #
b0 *
b0 ,
b1 .
b11 +
1$
1'
#5328
0%
#5994
1%
#6000
b10 3
b1 2
b1 "
b1 )
0$
0'
#6660
0%
#7000
b10 .
b11 +
1$
1'
#7326
1%
#7992
0%
#8000
b10 2
b10 "
b10 )
0$
0'
#8658
1%
#9000
b1 #
b1 *
b1 ,
b11 .
b11 +
1$
1'
#9324
0%
#9990
1%
#10000
b11 2
b11 "
b11 )
0$
0'
#10656
0%
#11000
b10 #
b10 *
b10 ,
b100 .
b11 +
1$
1'
#11322
1%
#11988
0%
#12000
b100 2
b100 "
b100 )
0$
0'
#12654
1%
#13000
b11 #
b11 *
b11 ,
b101 .
b11 +
1$
1'
#13320
0%
#13986
1%
#14000
b101 2
b101 "
b101 )
0$
0'
#14652
0%
#15000
b100 #
b100 *
b100 ,
b110 .
b11 +
1$
1'
#15318
1%
#15984
0%
#16000
b110 2
b110 "
b110 )
0$
0'
#16650
1%
#17000
b101 #
b101 *
b101 ,
b111 .
b11 +
1$
1'
#17316
0%
#17982
1%
#18000
b111 2
b111 "
b111 )
0$
0'
#18648
0%
#19000
b110 #
b110 *
b110 ,
b1000 .
b11 +
1$
1'
#19314
1%
#19980
0%
#20000
b0 2
b0 "
b0 )
b1 1
b1 !
b1 (
0$
0'
#20646
1%
#21000
b111 #
b111 *
b111 ,
b1001 .
b11 +
1$
1'
#21312
0%
#21978
1%
#22000
b1 2
b1 "
b1 )
0$
0'
#22644
0%
#23000
b1 #
b1 *
b1 ,
b1010 .
b11 +
1$
1'
#23310
1%
#23976
0%
#24000
b10 2
b10 "
b10 )
0$
0'
#24642
1%
#25000
b10 #
b10 *
b10 ,
b1011 .
b11 +
1$
1'
#25308
0%
#25974
1%
#26000
b11 2
b11 "
b11 )
0$
0'
#26640
0%
#27000
b11 #
b11 *
b11 ,
b1100 .
b11 +
1$
1'
#27306
1%
#27972
0%
#28000
b100 2
b100 "
b100 )
0$
0'
#28638
1%
#29000
b100 #
b100 *
b100 ,
b1101 .
b11 +
1$
1'
#29304
0%
#29970
1%
#30000
b101 2
b101 "
b101 )
0$
0'
#30636
0%
#31000
b101 #
b101 *
b101 ,
b1110 .
b11 +
1$
1'
#31302
1%
#31968
0%
#32000
b110 2
b110 "
b110 )
0$
0'
#32634
1%
#33000
b110 #
b110 *
b110 ,
b1111 .
b11 +
1$
1'
#33300
0%
#33966
1%
#34000
b111 2
b111 "
b111 )
0$
0'
#34632
0%
#35000
b111 #
b111 *
b111 ,
b10000 .
b11 +
1$
1'
#35298
1%
#35964
0%
#36000
b0 2
b0 "
b0 )
b10 1
b10 !
b10 (
0$
0'
#36630
1%
#37000
b1000 #
b1000 *
b1000 ,
b10001 .
b11 +
1$
1'
#37296
0%
#37962
1%
#38000
b1 2
b1 "
b1 )
0$
0'
#38628
0%
#39000
b10 #
b10 *
b10 ,
b10010 .
b11 +
1$
1'
#39294
1%
#39960
0%
#40000
b10 2
b10 "
b10 )
0$
0'
#40626
1%
#41000
b11 #
b11 *
b11 ,
b10011 .
b11 +
1$
1'
#41292
0%
#41958
1%
#42000
b11 2
b11 "
b11 )
0$
0'
#42624
0%
#43000
b100 #
b100 *
b100 ,
b10100 .
b11 +
1$
1'
#43290
1%
#43956
0%
#44000
b100 2
b100 "
b100 )
0$
0'
#44622
1%
#45000
b101 #
b101 *
b101 ,
b10101 .
b11 +
1$
1'
#45288
0%
#45954
1%
#46000
b101 2
b101 "
b101 )
0$
0'
#46620
0%
#47000
b110 #
b110 *
b110 ,
b10110 .
b11 +
1$
1'
#47286
1%
#47952
0%
#48000
b110 2
b110 "
b110 )
0$
0'
#48618
1%
#49000
b111 #
b111 *
b111 ,
b10111 .
b11 +
1$
1'
#49284
0%
#49950
1%
#50000
b111 2
b111 "
b111 )
0$
0'
#50616
0%
#51000
b1000 #
b1000 *
b1000 ,
b11000 .
b11 +
1$
1'
#51282
1%
#51948
0%
#52000
b0 2
b0 "
b0 )
b11 1
b11 !
b11 (
0$
0'
#52614
1%
#53000
b1001 #
b1001 *
b1001 ,
b11001 .
b11 +
1$
1'
#53280
0%
#53946
1%
#54000
b1 2
b1 "
b1 )
0$
0'
#54612
0%
#55000
b11 #
b11 *
b11 ,
b11010 .
b11 +
1$
1'
#55278
1%
#55944
0%
#56000
b10 2
b10 "
b10 )
0$
0'
#56610
1%
#57000
b100 #
b100 *
b100 ,
b11011 .
b11 +
1$
1'
#57276
0%
#57942
1%
#58000
b11 2
b11 "
b11 )
0$
0'
#58608
0%
#59000
b101 #
b101 *
b101 ,
b11100 .
b11 +
1$
1'
#59274
1%
#59940
0%
#60000
b100 2
b100 "
b100 )
0$
0'
#60606
1%
#61000
b110 #
b110 *
b110 ,
b11101 .
b11 +
1$
1'
#61272
0%
#61938
1%
#62000
b101 2
b101 "
b101 )
0$
0'
#62604
0%
#63000
b111 #
b111 *
b111 ,
b11110 .
b11 +
1$
1'
#63270
1%
#63936
0%
#64000
b110 2
b110 "
b110 )
0$
0'
#64602
1%
#65000
b1000 #
b1000 *
b1000 ,
b11111 .
b11 +
1$
1'
#65268
0%
#65934
1%
#66000
b111 2
b111 "
b111 )
0$
0'
#66600
0%
#67000
b1001 #
b1001 *
b1001 ,
b100000 .
b11 +
1$
1'
#67266
1%
#67932
0%
#68000
b0 2
b0 "
b0 )
b100 1
b100 !
b100 (
0$
0'
#68598
1%
#69000
b1010 #
b1010 *
b1010 ,
b100001 .
b11 +
1$
1'
#69264
0%
#69930
1%
#70000
b1 2
b1 "
b1 )
0$
0'
#70596
0%
#71000
b100 #
b100 *
b100 ,
b100010 .
b11 +
1$
1'
#71262
1%
#71928
0%
#72000
b10 2
b10 "
b10 )
0$
0'
#72594
1%
#73000
b101 #
b101 *
b101 ,
b100011 .
b11 +
1$
1'
#73260
0%
#73926
1%
#74000
b11 2
b11 "
b11 )
0$
0'
#74592
0%
#75000
b110 #
b110 *
b110 ,
b100100 .
b11 +
1$
1'
#75258
1%
#75924
0%
#76000
b100 2
b100 "
b100 )
0$
0'
#76590
1%
#77000
b111 #
b111 *
b111 ,
b100101 .
b11 +
1$
1'
#77256
0%
#77922
1%
#78000
b101 2
b101 "
b101 )
0$
0'
#78588
0%
#79000
b1000 #
b1000 *
b1000 ,
b100110 .
b11 +
1$
1'
#79254
1%
#79920
0%
#80000
b110 2
b110 "
b110 )
0$
0'
#80586
1%
#81000
b1001 #
b1001 *
b1001 ,
b100111 .
b11 +
1$
1'
#81252
0%
#81918
1%
#82000
b111 2
b111 "
b111 )
0$
0'
#82584
0%
#83000
b1010 #
b1010 *
b1010 ,
b101000 .
b11 +
1$
1'
#83250
1%
#83916
0%
#84000
b0 2
b0 "
b0 )
b101 1
b101 !
b101 (
0$
0'
#84582
1%
#85000
b1011 #
b1011 *
b1011 ,
b101001 .
b11 +
1$
1'
#85248
0%
#85914
1%
#86000
b1 2
b1 "
b1 )
0$
0'
#86580
0%
#87000
b101 #
b101 *
b101 ,
b101010 .
b11 +
1$
1'
#87246
1%
#87912
0%
#88000
b10 2
b10 "
b10 )
0$
0'
#88578
1%
#89000
b110 #
b110 *
b110 ,
b101011 .
b11 +
1$
1'
#89244
0%
#89910
1%
#90000
b11 2
b11 "
b11 )
0$
0'
#90576
0%
#91000
b111 #
b111 *
b111 ,
b101100 .
b11 +
1$
1'
#91242
1%
#91908
0%
#92000
b100 2
b100 "
b100 )
0$
0'
#92574
1%
#93000
b1000 #
b1000 *
b1000 ,
b101101 .
b11 +
1$
1'
#93240
0%
#93906
1%
#94000
b101 2
b101 "
b101 )
0$
0'
#94572
0%
#95000
b1001 #
b1001 *
b1001 ,
b101110 .
b11 +
1$
1'
#95238
1%
#95904
0%
#96000
b110 2
b110 "
b110 )
0$
0'
#96570
1%
#97000
b1010 #
b1010 *
b1010 ,
b101111 .
b11 +
1$
1'
#97236
0%
#97902
1%
#98000
b111 2
b111 "
b111 )
0$
0'
#98568
0%
#99000
b1011 #
b1011 *
b1011 ,
b110000 .
b11 +
1$
1'
